odoo/addons/brand_external_report_layout/README.rst
odoo/addons/brand_external_report_layout/__init__.py
odoo/addons/brand_external_report_layout/__manifest__.py
odoo/addons/brand_external_report_layout/i18n/brand_external_report_layout.pot
odoo/addons/brand_external_report_layout/i18n/es.po
odoo/addons/brand_external_report_layout/i18n/es_AR.po
odoo/addons/brand_external_report_layout/i18n/hr.po
odoo/addons/brand_external_report_layout/i18n/it.po
odoo/addons/brand_external_report_layout/i18n/nl.po
odoo/addons/brand_external_report_layout/models/__init__.py
odoo/addons/brand_external_report_layout/models/res_brand.py
odoo/addons/brand_external_report_layout/readme/CONTRIBUTORS.rst
odoo/addons/brand_external_report_layout/readme/DESCRIPTION.rst
odoo/addons/brand_external_report_layout/readme/ROADMAP.rst
odoo/addons/brand_external_report_layout/readme/USAGE.rst
odoo/addons/brand_external_report_layout/security/brand_document_layout.xml
odoo/addons/brand_external_report_layout/static/description/icon.png
odoo/addons/brand_external_report_layout/static/description/index.html
odoo/addons/brand_external_report_layout/tests/__init__.py
odoo/addons/brand_external_report_layout/tests/test_brand_external_report_layout.py
odoo/addons/brand_external_report_layout/views/report_template.xml
odoo/addons/brand_external_report_layout/views/res_brand.xml
odoo/addons/brand_external_report_layout/wizards/__init__.py
odoo/addons/brand_external_report_layout/wizards/brand_document_layout.py
odoo/addons/brand_external_report_layout/wizards/brand_document_layout.xml
odoo_addon_brand_external_report_layout-16.0.1.0.3.dist-info/METADATA
odoo_addon_brand_external_report_layout-16.0.1.0.3.dist-info/WHEEL
odoo_addon_brand_external_report_layout-16.0.1.0.3.dist-info/top_level.txt
odoo_addon_brand_external_report_layout-16.0.1.0.3.dist-info/RECORD
