Metadata-Version: 2.1
Name: odoo-addon-brand_external_report_layout
Version: 16.0.1.0.3
Summary: This module allows you to have a different layout by brand for your external reports.
Home-page: https://github.com/OCA/brand
Author: ACSONE SA/NV,Odoo Community Association (OCA)
Author-email: support@odoo-community.org
License: AGPL-3
Classifier: Programming Language :: Python
Classifier: Framework :: Odoo
Classifier: Framework :: Odoo :: 16.0
Classifier: License :: OSI Approved :: GNU Affero General Public License v3
Requires-Python: >=3.10
Requires-Dist: odoo-addon-brand<16.1dev,>=16.0dev
Requires-Dist: odoo<16.1dev,>=16.0a
